MANIFEST.in
README.md
pyproject.toml
setup.cfg
file_grid/__init__.py
file_grid/__main__.py
file_grid/algorithm.py
file_grid/engine.py
file_grid/files.py
file_grid/grid_builtins.py
file_grid/parsing.py
file_grid/template.py
file_grid/tools.py
file_grid.egg-info/PKG-INFO
file_grid.egg-info/SOURCES.txt
file_grid.egg-info/dependency_links.txt
file_grid.egg-info/entry_points.txt
file_grid.egg-info/top_level.txt