Metadata-Version: 2.1
Name: file-grid
Version: 0.0.2
Summary: Clone and multiply your files seamlessly using a simple template language
Author: pulkin
Author-email: gpulkin@gmail.com
